{"skeleton":{"hash":"Alh4St0MkhhkjNbyeqytZgYTAzY","spine":"3.8.67","x":-39.09,"y":-35.09,"width":106,"height":103,"images":"","audio":""},"bones":[{"name":"root"},{"name":"bone","parent":"root","x":7.04,"y":8},{"name":"2","parent":"bone","x":-2.98,"y":-1.82}],"slots":[{"name":"2","bone":"2","attachment":"1"}],"skins":[{"name":"default","attachments":{"2":{"1":{"x":9.85,"y":10.23,"width":106,"height":103},"2":{"x":5.89,"y":6.45,"width":111,"height":109}}}}],"animations":{"animation":{"slots":{"2":{"color":[{"color":"ffffff95"}],"attachment":[{"time":0.1333,"name":"2"},{"time":0.2667,"name":"1"}]}},"bones":{"2":{"translate":[{},{"time":0.1333,"y":2.41},{"time":0.2667}],"scale":[{"x":0.58,"y":0.58}]}}}}}